davat/__init__.py
davat/davat.py
davat-0.0.7.dist-info/LICENSE
davat-0.0.7.dist-info/METADATA
davat-0.0.7.dist-info/WHEEL
davat-0.0.7.dist-info/top_level.txt
davat-0.0.7.dist-info/RECORD
