Metadata-Version: 2.1
Name: davat
Version: 0.0.7
Summary: davat(دوات) is a very simple tools for normalizeing and cleaning Persian text
Home-page: https://github.com/mh-salari/davat
Author: MohammadHossein Salari
Author-email: mohammad.hossein.salari@gmail.com
License: MIT
Platform: UNKNOWN
Classifier: License :: OSI Approved :: MIT License
Classifier: Programming Language :: Python :: 3
Requires-Dist: emoji (>=1.2.0)
